femtow/__init__.py
femtow/app.py
femtow/decorators/__init__.py
femtow/decorators/renderers.py
femtow/decorators/routes.py
femtow/decorators/views.py
femtow/defaults/__init__.py
femtow/defaults/view_params.py
femtow-0.2.6.dist-info/LICENSE
femtow-0.2.6.dist-info/WHEEL
femtow-0.2.6.dist-info/METADATA
femtow-0.2.6.dist-info/RECORD
